llmvsllm/arena/bot_base.py
llmvsllm/arena/bot_pair.py
llmvsllm/arena/conversation.py
llmvsllm/arena/fixed_response_bot.py
llmvsllm/arena/human_input_bot.py
llmvsllm/arena/llm_bot.py
llmvsllm/bots/generic_llm_bots.py
llmvsllm/bots/system_bots.py
llmvsllm/console.py
llmvsllm/library/classes.py
llmvsllm/library/consts.py
llmvsllm/library/env.py
llmvsllm/library/log.py
llmvsllm/library/sound.py
llmvsllm-0.1.0.dist-info/LICENSE
llmvsllm-0.1.0.dist-info/METADATA
llmvsllm-0.1.0.dist-info/WHEEL
llmvsllm-0.1.0.dist-info/entry_points.txt
llmvsllm-0.1.0.dist-info/RECORD
